polaritonic_index/__init__.py
polaritonic_index/clustering_structure.py
polaritonic_index/data_analysis.py
polaritonic_index/main_TDDFT.py
polaritonic_index/main_groundstate.py
polaritonic_index/read_file.py
polaritonic_index/utils.py
polaritonic_index-0.1.0.dist-info/LICENSE
polaritonic_index-0.1.0.dist-info/METADATA
polaritonic_index-0.1.0.dist-info/WHEEL
polaritonic_index-0.1.0.dist-info/entry_points.txt
polaritonic_index-0.1.0.dist-info/RECORD
