Metadata-Version: 2.1
Name: polaritonic-index
Version: 0.1.0
Summary: Polaritonic Index (PI) is a computational tool designed to analyze and classify excitations in hybrid systems composed of a metal nanoparticle and one or more molecules. By examining transition density file, PI can differentiate between metal, molecular and 'hybrid' excitations (these could be polaritonic or charge transfer excitations).
Author: Lucia Cascino
Author-email: lucia.cascino@unisalento.it
Maintainer: Lucia Cascino
Maintainer-email: lucia.cascino@unisalento.it
Requires-Python: >=3.9.6,<3.13
Classifier: Programming Language :: Python :: 3
Classifier: Programming Language :: Python :: 3.10
Classifier: Programming Language :: Python :: 3.11
Classifier: Programming Language :: Python :: 3.12
Requires-Dist: matplotlib (>=3.9.2,<4.0.0)
Requires-Dist: pymatgen (>=2024.8.9,<2025.0.0)
Requires-Dist: rich-click (>=1.8.4,<2.0.0)
Requires-Dist: scikit-learn (>=1.5.2,<2.0.0)
